{
  "hash": "89cb8d8bceb697aab1500cf3241600140746e64d8134dfe8765358e59af637a8",
  "inks": [
    "sapphire",
    "amber"
  ],
  "cards": [
    {
      "amount": 4,
      "name": "Alice",
      "version": "Savvy Sailor"
    },
    {
      "amount": 3,
      "name": "Anna",
      "version": "Braving the Storm"
    },
    {
      "amount": 2,
      "name": "Aurora",
      "version": "Dreaming Guardian"
    },
    {
      "amount": 4,
      "name": "Aurora",
      "version": "Holding Court"
    },
    {
      "amount": 3,
      "name": "Chief Powhatan",
      "version": "Protective Leader"
    },
    {
      "amount": 4,
      "name": "Daisy Duck",
      "version": "Donald's Date"
    },
    {
      "amount": 2,
      "name": "Darling Dear",
      "version": "Beloved Wife"
    },
    {
      "amount": 4,
      "name": "Lady",
      "version": "Family Dog"
    },
    {
      "amount": 4,
      "name": "Lilo",
      "version": "Escape Artist"
    },
    {
      "amount": 4,
      "name": "Mowgli",
      "version": "Man Cub"
    },
    {
      "amount": 2,
      "name": "Nani",
      "version": "Stage Manager"
    },
    {
      "amount": 4,
      "name": "Ohana Means Family",
      "version": ""
    },
    {
      "amount": 4,
      "name": "Patch",
      "version": "Playful Pup"
    },
    {
      "amount": 4,
      "name": "Rajah",
      "version": "Devoted Protector"
    },
    {
      "amount": 4,
      "name": "Splatter Phoenix",
      "version": "Rejected Artist"
    },
    {
      "amount": 4,
      "name": "Thunderbolt",
      "version": "Wonder Dog"
    },
    {
      "amount": 4,
      "name": "Tiana",
      "version": "Restaurant Owner"
    }
  ]
}