{
  "hash": "6673b3abd16c9491a08599f8bd99134230c1816c7ee0ec8b9396d998d988b1ad",
  "inks": [
    "amber",
    "steel"
  ],
  "cards": [
    {
      "amount": 4,
      "name": "Ariel",
      "version": "Ethereal Voice"
    },
    {
      "amount": 4,
      "name": "Aurora",
      "version": "Holding Court"
    },
    {
      "amount": 3,
      "name": "Beyond the Horizon",
      "version": ""
    },
    {
      "amount": 3,
      "name": "Black Heron",
      "version": "Real Bad Egg"
    },
    {
      "amount": 4,
      "name": "Circle of Life",
      "version": ""
    },
    {
      "amount": 2,
      "name": "Gazelle",
      "version": "Ballad Singer"
    },
    {
      "amount": 3,
      "name": "He Hurled His Thunderbolt",
      "version": ""
    },
    {
      "amount": 4,
      "name": "Lexington",
      "version": "Small in Stature"
    },
    {
      "amount": 2,
      "name": "Look at This Family",
      "version": ""
    },
    {
      "amount": 4,
      "name": "Mickey Mouse",
      "version": "Amber Champion"
    },
    {
      "amount": 1,
      "name": "Mickey Mouse",
      "version": "Giant Mouse"
    },
    {
      "amount": 2,
      "name": "Mowgli",
      "version": "Man Cub"
    },
    {
      "amount": 4,
      "name": "Mulan",
      "version": "Disguised Soldier"
    },
    {
      "amount": 3,
      "name": "Namaari",
      "version": "Single-Minded Rival"
    },
    {
      "amount": 2,
      "name": "Pluto",
      "version": "Steel Champion"
    },
    {
      "amount": 3,
      "name": "Rajah",
      "version": "Devoted Protector"
    },
    {
      "amount": 2,
      "name": "Stitch",
      "version": "Carefree Surfer"
    },
    {
      "amount": 4,
      "name": "Strength of a Raging Fire",
      "version": ""
    },
    {
      "amount": 4,
      "name": "The Troubadour",
      "version": "Musical Narrator"
    },
    {
      "amount": 2,
      "name": "World's Greatest Criminal Mind",
      "version": ""
    }
  ]
}