{
  "hash": "c060f29fed4bfb4d2c5959122316b2c5107a1c98d8c865bcd24d8fa0a29eceb4",
  "inks": [
    "amethyst",
    "ruby"
  ],
  "cards": [
    {
      "amount": 2,
      "name": "Bronx",
      "version": "Ferocious Beast"
    },
    {
      "amount": 4,
      "name": "Cheshire Cat",
      "version": "Inexplicable"
    },
    {
      "amount": 4,
      "name": "Demona",
      "version": "Scourge of the Wyvern Clan"
    },
    {
      "amount": 4,
      "name": "Diablo",
      "version": "Watchful Raven"
    },
    {
      "amount": 2,
      "name": "Dragon Fire",
      "version": ""
    },
    {
      "amount": 4,
      "name": "Dumbo",
      "version": "Ninth Wonder of the Universe"
    },
    {
      "amount": 4,
      "name": "Elsa",
      "version": "The Fifth Spirit"
    },
    {
      "amount": 4,
      "name": "Genie",
      "version": "Wish Fulfilled"
    },
    {
      "amount": 2,
      "name": "Hercules",
      "version": "Mighty Leader"
    },
    {
      "amount": 3,
      "name": "Iago",
      "version": "Giant Spectral Parrot"
    },
    {
      "amount": 3,
      "name": "Junior Woodchuck Guidebook",
      "version": ""
    },
    {
      "amount": 3,
      "name": "Lumiere",
      "version": "Fiery Friend"
    },
    {
      "amount": 3,
      "name": "Maui",
      "version": "Half-Shark"
    },
    {
      "amount": 3,
      "name": "Palace Guard",
      "version": "Spectral Sentry"
    },
    {
      "amount": 4,
      "name": "Sisu",
      "version": "Emboldened Warrior"
    },
    {
      "amount": 3,
      "name": "The Headless Horseman",
      "version": "Terror of Sleepy Hollow"
    },
    {
      "amount": 4,
      "name": "Tinker Bell",
      "version": "Fancy Footwork"
    },
    {
      "amount": 2,
      "name": "Ursula",
      "version": "Whisper of Vanessa"
    },
    {
      "amount": 2,
      "name": "Vanellope Von Schweetz",
      "version": "Spunky Speedster"
    }
  ]
}