{
  "hash": "d495641bc321a299c3387d972a431f97d9d78c9bfacab9cada3573f2756094bf",
  "inks": [
    "ruby",
    "amethyst"
  ],
  "cards": [
    {
      "amount": 4,
      "name": "Cheshire Cat",
      "version": "Inexplicable"
    },
    {
      "amount": 3,
      "name": "Demona",
      "version": "Scourge of the Wyvern Clan"
    },
    {
      "amount": 3,
      "name": "Diablo",
      "version": "Obedient Raven"
    },
    {
      "amount": 4,
      "name": "Diablo",
      "version": "Watchful Raven"
    },
    {
      "amount": 4,
      "name": "Dumbo",
      "version": "Ninth Wonder of the Universe"
    },
    {
      "amount": 4,
      "name": "Elsa",
      "version": "The Fifth Spirit"
    },
    {
      "amount": 4,
      "name": "Genie",
      "version": "Wish Fulfilled"
    },
    {
      "amount": 3,
      "name": "Hades",
      "version": "Looking for a Deal"
    },
    {
      "amount": 1,
      "name": "Hercules",
      "version": "Mighty Leader"
    },
    {
      "amount": 2,
      "name": "Iago",
      "version": "Giant Spectral Parrot"
    },
    {
      "amount": 4,
      "name": "Lumiere",
      "version": "Fiery Friend"
    },
    {
      "amount": 1,
      "name": "Madam Mim",
      "version": "Elephant"
    },
    {
      "amount": 3,
      "name": "Mother Gothel",
      "version": "Vain Sorceress"
    },
    {
      "amount": 3,
      "name": "Next Stop, Olympus",
      "version": ""
    },
    {
      "amount": 4,
      "name": "Palace Guard",
      "version": "Spectral Sentry"
    },
    {
      "amount": 2,
      "name": "Peter Pan",
      "version": "High Flyer"
    },
    {
      "amount": 3,
      "name": "Sisu",
      "version": "Emboldened Warrior"
    },
    {
      "amount": 3,
      "name": "The Headless Horseman",
      "version": "Terror of Sleepy Hollow"
    },
    {
      "amount": 1,
      "name": "They Never Come Back",
      "version": ""
    },
    {
      "amount": 3,
      "name": "Tinker Bell",
      "version": "Fancy Footwork"
    },
    {
      "amount": 1,
      "name": "Ursula",
      "version": "Whisper of Vanessa"
    }
  ]
}