{
  "hash": "e1186639cb0a892a466ddade0c95ec4e31a9df33b258add0ca2a6094b307d922",
  "inks": [
    "ruby",
    "amethyst"
  ],
  "cards": [
    {
      "amount": 4,
      "name": "Be King Undisputed",
      "version": ""
    },
    {
      "amount": 2,
      "name": "Demona",
      "version": "Scourge of the Wyvern Clan"
    },
    {
      "amount": 2,
      "name": "Dragon Fire",
      "version": ""
    },
    {
      "amount": 4,
      "name": "Elsa",
      "version": "Exploring the Unknown"
    },
    {
      "amount": 4,
      "name": "Elsa",
      "version": "Snow Queen"
    },
    {
      "amount": 3,
      "name": "Elsa",
      "version": "Spirit of Winter"
    },
    {
      "amount": 4,
      "name": "Elsa",
      "version": "The Fifth Spirit"
    },
    {
      "amount": 4,
      "name": "Finders Keepers",
      "version": ""
    },
    {
      "amount": 4,
      "name": "Genie",
      "version": "Wish Fulfilled"
    },
    {
      "amount": 3,
      "name": "Gwythaint",
      "version": "Savage Hunter"
    },
    {
      "amount": 4,
      "name": "Lumiere",
      "version": "Fiery Friend"
    },
    {
      "amount": 3,
      "name": "Madam Mim",
      "version": "Tiny Adversary"
    },
    {
      "amount": 4,
      "name": "Mother Gothel",
      "version": "Vain Sorceress"
    },
    {
      "amount": 4,
      "name": "Palace Guard",
      "version": "Spectral Sentry"
    },
    {
      "amount": 4,
      "name": "Rafiki",
      "version": "Mystical Fighter"
    },
    {
      "amount": 4,
      "name": "Te Kā",
      "version": "Elemental Terror"
    },
    {
      "amount": 4,
      "name": "Te Kā",
      "version": "Lava Monster"
    }
  ]
}