{
  "hash": "29bc9bb645f3e01b0a5e15b0356c62327acb53c700a012277697e03e5b497add",
  "inks": [
    "amethyst",
    "steel"
  ],
  "cards": [
    {
      "amount": 4,
      "name": "Amethyst Chromicon",
      "version": ""
    },
    {
      "amount": 4,
      "name": "Calhoun",
      "version": "Marine Sergeant"
    },
    {
      "amount": 4,
      "name": "Captain Hook",
      "version": "Forceful Duelist"
    },
    {
      "amount": 4,
      "name": "Castle Wyvern",
      "version": "Above the Clouds"
    },
    {
      "amount": 4,
      "name": "Doc",
      "version": "Bold Knight"
    },
    {
      "amount": 2,
      "name": "Elsa's Ice Palace",
      "version": "Place of Solitude"
    },
    {
      "amount": 4,
      "name": "Fairy Ship",
      "version": "Royal Vessel"
    },
    {
      "amount": 4,
      "name": "Fire the Cannons!",
      "version": ""
    },
    {
      "amount": 4,
      "name": "Giant Cobra",
      "version": "Ghostly Serpent"
    },
    {
      "amount": 2,
      "name": "Honeymaren",
      "version": "Northuldra Guide"
    },
    {
      "amount": 4,
      "name": "John Silver",
      "version": "Greedy Treasure Seeker"
    },
    {
      "amount": 1,
      "name": "Lilo",
      "version": "Bundled Up"
    },
    {
      "amount": 4,
      "name": "Mulan",
      "version": "Disguised Soldier"
    },
    {
      "amount": 4,
      "name": "Nala",
      "version": "Undaunted Lioness"
    },
    {
      "amount": 4,
      "name": "Seven Dwarfs' Mine",
      "version": "Secure Fortress"
    },
    {
      "amount": 4,
      "name": "The White Rose",
      "version": "Jewel of the Garden"
    },
    {
      "amount": 4,
      "name": "Zootopia",
      "version": "Police Headquarters"
    }
  ]
}