{
  "hash": "5892e62f45962402f0bb7d10df5c8e161c598eb41b4546375e0642fd5ff17eda",
  "inks": [
    "sapphire",
    "amethyst"
  ],
  "cards": [
    {
      "amount": 4,
      "name": "Basil",
      "version": "Practiced Detective"
    },
    {
      "amount": 4,
      "name": "Cheshire Cat",
      "version": "Inexplicable"
    },
    {
      "amount": 3,
      "name": "Demona",
      "version": "Scourge of the Wyvern Clan"
    },
    {
      "amount": 4,
      "name": "Dumbo",
      "version": "Ninth Wonder of the Universe"
    },
    {
      "amount": 4,
      "name": "Elsa",
      "version": "The Fifth Spirit"
    },
    {
      "amount": 4,
      "name": "Genie",
      "version": "Wish Fulfilled"
    },
    {
      "amount": 4,
      "name": "Hades",
      "version": "Infernal Schemer"
    },
    {
      "amount": 2,
      "name": "Hades",
      "version": "Looking for a Deal"
    },
    {
      "amount": 4,
      "name": "Into the Unknown",
      "version": ""
    },
    {
      "amount": 3,
      "name": "Junior Woodchuck Guidebook",
      "version": ""
    },
    {
      "amount": 2,
      "name": "Let It Go",
      "version": ""
    },
    {
      "amount": 4,
      "name": "Pete",
      "version": "Ghost of Christmas Future"
    },
    {
      "amount": 4,
      "name": "Royal Guard",
      "version": "Octopus Soldier"
    },
    {
      "amount": 4,
      "name": "Sail the Azurite Sea",
      "version": ""
    },
    {
      "amount": 2,
      "name": "Spooky Sight",
      "version": ""
    },
    {
      "amount": 3,
      "name": "Sven",
      "version": "Leaping Reindeer"
    },
    {
      "amount": 4,
      "name": "Tipo",
      "version": "Growing Son"
    },
    {
      "amount": 1,
      "name": "Wasabi",
      "version": "Methodical Engineer"
    }
  ]
}