{
  "hash": "91703ea36decbeaa35300e032f535daa14d3df5ce3bddcc1ce201e02b972f00d",
  "inks": [
    "sapphire",
    "amethyst"
  ],
  "cards": [
    {
      "amount": 4,
      "name": "Basil",
      "version": "Practiced Detective"
    },
    {
      "amount": 4,
      "name": "Cheshire Cat",
      "version": "Inexplicable"
    },
    {
      "amount": 4,
      "name": "Demona",
      "version": "Scourge of the Wyvern Clan"
    },
    {
      "amount": 4,
      "name": "Dumbo",
      "version": "Ninth Wonder of the Universe"
    },
    {
      "amount": 4,
      "name": "Elsa",
      "version": "The Fifth Spirit"
    },
    {
      "amount": 4,
      "name": "Genie",
      "version": "Wish Fulfilled"
    },
    {
      "amount": 4,
      "name": "Hades",
      "version": "Infernal Schemer"
    },
    {
      "amount": 4,
      "name": "Hades",
      "version": "Looking for a Deal"
    },
    {
      "amount": 1,
      "name": "Hypnotic Strength",
      "version": ""
    },
    {
      "amount": 3,
      "name": "Into the Unknown",
      "version": ""
    },
    {
      "amount": 4,
      "name": "Junior Woodchuck Guidebook",
      "version": ""
    },
    {
      "amount": 4,
      "name": "Let It Go",
      "version": ""
    },
    {
      "amount": 4,
      "name": "Rafiki",
      "version": "Mystical Fighter"
    },
    {
      "amount": 4,
      "name": "Sail the Azurite Sea",
      "version": ""
    },
    {
      "amount": 1,
      "name": "Second Star to the Right",
      "version": ""
    },
    {
      "amount": 1,
      "name": "Sven",
      "version": "Leaping Reindeer"
    },
    {
      "amount": 1,
      "name": "Tigger",
      "version": "Bouncing All the Way"
    },
    {
      "amount": 4,
      "name": "Tipo",
      "version": "Growing Son"
    },
    {
      "amount": 1,
      "name": "Wasabi",
      "version": "Methodical Engineer"
    }
  ]
}