{
  "hash": "91f6d0ec3e899c6c79e06b93fc4d5a27136ed7284a502df47a8789d7afebe787",
  "inks": [
    "amethyst",
    "sapphire"
  ],
  "cards": [
    {
      "amount": 2,
      "name": "All Is Found",
      "version": ""
    },
    {
      "amount": 3,
      "name": "Anna",
      "version": "Braving the Storm"
    },
    {
      "amount": 3,
      "name": "Anna",
      "version": "Ice Breaker"
    },
    {
      "amount": 2,
      "name": "Anna",
      "version": "Magical Mission"
    },
    {
      "amount": 1,
      "name": "Anna",
      "version": "Mystical Majesty"
    },
    {
      "amount": 2,
      "name": "Anna",
      "version": "True-Hearted"
    },
    {
      "amount": 3,
      "name": "Anna",
      "version": "Trusting Sister"
    },
    {
      "amount": 1,
      "name": "Atlantean Crystal",
      "version": ""
    },
    {
      "amount": 1,
      "name": "Aurelian Gyrosensor",
      "version": ""
    },
    {
      "amount": 2,
      "name": "B.E.N.",
      "version": "Eccentric Robot"
    },
    {
      "amount": 1,
      "name": "Basil",
      "version": "Practiced Detective"
    },
    {
      "amount": 2,
      "name": "Bruni",
      "version": "Fire Salamander"
    },
    {
      "amount": 2,
      "name": "Develop Your Brain",
      "version": ""
    },
    {
      "amount": 1,
      "name": "Elsa",
      "version": "Fierce Protector"
    },
    {
      "amount": 2,
      "name": "Elsa",
      "version": "Gloves Off"
    },
    {
      "amount": 1,
      "name": "Elsa",
      "version": "Ice Maker"
    },
    {
      "amount": 1,
      "name": "Elsa",
      "version": "The Fifth Spirit"
    },
    {
      "amount": 3,
      "name": "Elsa",
      "version": "Trusted Sister"
    },
    {
      "amount": 1,
      "name": "Forest Duel",
      "version": ""
    },
    {
      "amount": 1,
      "name": "Gale",
      "version": "Wind Spirit"
    },
    {
      "amount": 1,
      "name": "Genie",
      "version": "Supportive Friend"
    },
    {
      "amount": 2,
      "name": "Hans",
      "version": "Noble Scoundrel"
    },
    {
      "amount": 1,
      "name": "Heads Held High",
      "version": ""
    },
    {
      "amount": 2,
      "name": "Honeymaren",
      "version": "Northuldra Guide"
    },
    {
      "amount": 1,
      "name": "Ice Spikes",
      "version": ""
    },
    {
      "amount": 1,
      "name": "Into the Unknown",
      "version": ""
    },
    {
      "amount": 3,
      "name": "Olaf",
      "version": "Recapping the Story"
    },
    {
      "amount": 1,
      "name": "Pinocchio",
      "version": "Strings Attached"
    },
    {
      "amount": 2,
      "name": "Ryder",
      "version": "Fleet-Footed Infiltrator"
    },
    {
      "amount": 1,
      "name": "Sail the Azurite Sea",
      "version": ""
    },
    {
      "amount": 2,
      "name": "Sisu",
      "version": "In Her Element"
    },
    {
      "amount": 2,
      "name": "Sven",
      "version": "Keen-Eyed Reindeer"
    },
    {
      "amount": 1,
      "name": "The Nokk",
      "version": "Mythical Spirit"
    },
    {
      "amount": 2,
      "name": "The White Rose",
      "version": "Jewel of the Garden"
    },
    {
      "amount": 1,
      "name": "They Never Come Back",
      "version": ""
    },
    {
      "amount": 2,
      "name": "Yelana",
      "version": "Northuldra Leader"
    }
  ]
}