{
  "hash": "95b7e046606b9110d0960bc258a4c3c17fa41bbfd12d5016842b7b0e4160c05e",
  "inks": [
    "sapphire",
    "amethyst"
  ],
  "cards": [
    {
      "amount": 1,
      "name": "Belle",
      "version": "Accomplished Mystic"
    },
    {
      "amount": 2,
      "name": "Cheshire Cat",
      "version": "Inexplicable"
    },
    {
      "amount": 1,
      "name": "Develop Your Brain",
      "version": ""
    },
    {
      "amount": 2,
      "name": "Diablo",
      "version": "Obedient Raven"
    },
    {
      "amount": 2,
      "name": "Elsa",
      "version": "Spirit of Winter"
    },
    {
      "amount": 4,
      "name": "Elsa",
      "version": "The Fifth Spirit"
    },
    {
      "amount": 1,
      "name": "Fragile as a Flower",
      "version": ""
    },
    {
      "amount": 2,
      "name": "Genie",
      "version": "Wish Fulfilled"
    },
    {
      "amount": 2,
      "name": "Hades",
      "version": "Infernal Schemer"
    },
    {
      "amount": 2,
      "name": "Hades",
      "version": "Lord of the Dead"
    },
    {
      "amount": 3,
      "name": "Iago",
      "version": "Stompin' Mad"
    },
    {
      "amount": 4,
      "name": "Into the Unknown",
      "version": ""
    },
    {
      "amount": 4,
      "name": "Junior Woodchuck Guidebook",
      "version": ""
    },
    {
      "amount": 2,
      "name": "Kristoff",
      "version": "Mining the Ruins"
    },
    {
      "amount": 1,
      "name": "Last",
      "version": "Ditch Effort"
    },
    {
      "amount": 2,
      "name": "Madam Mim",
      "version": "Elephant"
    },
    {
      "amount": 2,
      "name": "Monstro",
      "version": "Infamous Whale"
    },
    {
      "amount": 3,
      "name": "Olaf",
      "version": "Helping Hand"
    },
    {
      "amount": 2,
      "name": "One Jump Ahead",
      "version": ""
    },
    {
      "amount": 2,
      "name": "Pinocchio",
      "version": "Strings Attached"
    },
    {
      "amount": 2,
      "name": "Royal Guard",
      "version": "Octopus Soldier"
    },
    {
      "amount": 4,
      "name": "Sail the Azurite Sea",
      "version": ""
    },
    {
      "amount": 2,
      "name": "Sudden Scare",
      "version": ""
    },
    {
      "amount": 4,
      "name": "They Never Come Back",
      "version": ""
    },
    {
      "amount": 4,
      "name": "Tipo",
      "version": "Growing Son"
    },
    {
      "amount": 2,
      "name": "Ursula",
      "version": "Whisper of Vanessa"
    },
    {
      "amount": 1,
      "name": "Vision of the Future",
      "version": ""
    }
  ]
}