{
  "hash": "b16b08d7785d2df45d24c4a0b542ee3b0083bb1c74cf8de58583185b76bfa873",
  "inks": [
    "sapphire",
    "amethyst"
  ],
  "cards": [
    {
      "amount": 4,
      "name": "Basil",
      "version": "Practiced Detective"
    },
    {
      "amount": 4,
      "name": "Cheshire Cat",
      "version": "Inexplicable"
    },
    {
      "amount": 4,
      "name": "Demona",
      "version": "Scourge of the Wyvern Clan"
    },
    {
      "amount": 4,
      "name": "Elsa",
      "version": "The Fifth Spirit"
    },
    {
      "amount": 4,
      "name": "Genie",
      "version": "Wish Fulfilled"
    },
    {
      "amount": 4,
      "name": "Hades",
      "version": "Infernal Schemer"
    },
    {
      "amount": 4,
      "name": "Hades",
      "version": "Looking for a Deal"
    },
    {
      "amount": 4,
      "name": "Iago",
      "version": "Giant Spectral Parrot"
    },
    {
      "amount": 3,
      "name": "Into the Unknown",
      "version": ""
    },
    {
      "amount": 3,
      "name": "Junior Woodchuck Guidebook",
      "version": ""
    },
    {
      "amount": 4,
      "name": "Let It Go",
      "version": ""
    },
    {
      "amount": 2,
      "name": "Pete",
      "version": "Ghost of Christmas Future"
    },
    {
      "amount": 4,
      "name": "Royal Guard",
      "version": "Octopus Soldier"
    },
    {
      "amount": 4,
      "name": "Sail the Azurite Sea",
      "version": ""
    },
    {
      "amount": 1,
      "name": "Sven",
      "version": "Leaping Reindeer"
    },
    {
      "amount": 3,
      "name": "Tigger",
      "version": "Bouncing All the Way"
    },
    {
      "amount": 4,
      "name": "Tipo",
      "version": "Growing Son"
    }
  ]
}