{
  "hash": "c0d9ce7dfa19885a35953a71d4f526bbf09db7aa0e411d00f82a49e0735577a0",
  "inks": [
    "amber",
    "amethyst"
  ],
  "cards": [
    {
      "amount": 4,
      "name": "Cheshire Cat",
      "version": "Inexplicable"
    },
    {
      "amount": 4,
      "name": "Demona",
      "version": "Scourge of the Wyvern Clan"
    },
    {
      "amount": 2,
      "name": "Dumbo",
      "version": "Ninth Wonder of the Universe"
    },
    {
      "amount": 4,
      "name": "Eilonwy",
      "version": "Princess of Llyr"
    },
    {
      "amount": 4,
      "name": "Elsa",
      "version": "The Fifth Spirit"
    },
    {
      "amount": 2,
      "name": "Genie",
      "version": "Wish Fulfilled"
    },
    {
      "amount": 4,
      "name": "Grandmother Willow",
      "version": "Ancient Advisor"
    },
    {
      "amount": 4,
      "name": "Hades",
      "version": "Looking for a Deal"
    },
    {
      "amount": 1,
      "name": "Hypnotic Strength",
      "version": ""
    },
    {
      "amount": 1,
      "name": "Iago",
      "version": "Giant Spectral Parrot"
    },
    {
      "amount": 3,
      "name": "Junior Woodchuck Guidebook",
      "version": ""
    },
    {
      "amount": 1,
      "name": "Magical Maneuvers",
      "version": ""
    },
    {
      "amount": 3,
      "name": "Mowgli",
      "version": "Man Cub"
    },
    {
      "amount": 1,
      "name": "Palace Guard",
      "version": "Spectral Sentry"
    },
    {
      "amount": 3,
      "name": "Raging Storm",
      "version": ""
    },
    {
      "amount": 3,
      "name": "Royal Guard",
      "version": "Octopus Soldier"
    },
    {
      "amount": 2,
      "name": "Stitch",
      "version": "Carefree Surfer"
    },
    {
      "amount": 2,
      "name": "Sven",
      "version": "Leaping Reindeer"
    },
    {
      "amount": 4,
      "name": "The Horseman Strikes!",
      "version": ""
    },
    {
      "amount": 3,
      "name": "The Library",
      "version": "A Gift for Belle"
    },
    {
      "amount": 3,
      "name": "Tigger",
      "version": "Bouncing All the Way"
    },
    {
      "amount": 2,
      "name": "World's Greatest Criminal Mind",
      "version": ""
    }
  ]
}