{
  "hash": "d18777ec8e6150404aef43ff120ad8c920b9d0baee1efabbab3f78a09a40822b",
  "inks": [
    "amber",
    "amethyst"
  ],
  "cards": [
    {
      "amount": 2,
      "name": "Belle",
      "version": "Accomplished Mystic"
    },
    {
      "amount": 4,
      "name": "Cheshire Cat",
      "version": "Inexplicable"
    },
    {
      "amount": 4,
      "name": "Demona",
      "version": "Scourge of the Wyvern Clan"
    },
    {
      "amount": 4,
      "name": "Dumbo",
      "version": "Ninth Wonder of the Universe"
    },
    {
      "amount": 4,
      "name": "Eilonwy",
      "version": "Princess of Llyr"
    },
    {
      "amount": 1,
      "name": "Elsa",
      "version": "Spirit of Winter"
    },
    {
      "amount": 4,
      "name": "Elsa",
      "version": "The Fifth Spirit"
    },
    {
      "amount": 4,
      "name": "Genie",
      "version": "Wish Fulfilled"
    },
    {
      "amount": 3,
      "name": "Hades",
      "version": "Looking for a Deal"
    },
    {
      "amount": 3,
      "name": "Iago",
      "version": "Giant Spectral Parrot"
    },
    {
      "amount": 3,
      "name": "Iago",
      "version": "Stompin' Mad"
    },
    {
      "amount": 4,
      "name": "Junior Woodchuck Guidebook",
      "version": ""
    },
    {
      "amount": 4,
      "name": "Lantern",
      "version": ""
    },
    {
      "amount": 4,
      "name": "Mowgli",
      "version": "Man Cub"
    },
    {
      "amount": 1,
      "name": "Retrosphere",
      "version": ""
    },
    {
      "amount": 4,
      "name": "Royal Guard",
      "version": "Octopus Soldier"
    },
    {
      "amount": 4,
      "name": "The Horseman Strikes!",
      "version": ""
    },
    {
      "amount": 3,
      "name": "World's Greatest Criminal Mind",
      "version": ""
    }
  ]
}