{
  "hash": "11a4eceff8848f85810394d902534e3b2f7211997da196f82e232254277bc292",
  "inks": [
    "amethyst",
    "emerald"
  ],
  "cards": [
    {
      "amount": 4,
      "name": "Amethyst Chromicon",
      "version": ""
    },
    {
      "amount": 4,
      "name": "Cursed Merfolk",
      "version": "Ursula's Handiwork"
    },
    {
      "amount": 4,
      "name": "Diablo",
      "version": "Obedient Raven"
    },
    {
      "amount": 4,
      "name": "Enigmatic Inkcaster",
      "version": ""
    },
    {
      "amount": 2,
      "name": "Family Fishing Pole",
      "version": ""
    },
    {
      "amount": 4,
      "name": "Fred",
      "version": "Mascot by Day"
    },
    {
      "amount": 4,
      "name": "Gathering Knowledge and Wisdom",
      "version": ""
    },
    {
      "amount": 2,
      "name": "Go Go Tomago",
      "version": "Darting Dynamo"
    },
    {
      "amount": 4,
      "name": "Honeymaren",
      "version": "Northuldra Guide"
    },
    {
      "amount": 4,
      "name": "Little John",
      "version": "Camp Cook"
    },
    {
      "amount": 4,
      "name": "Palace Guard",
      "version": "Spectral Sentry"
    },
    {
      "amount": 4,
      "name": "Pegasus",
      "version": "Gift for Hercules"
    },
    {
      "amount": 2,
      "name": "Royal Guard",
      "version": "Octopus Soldier"
    },
    {
      "amount": 2,
      "name": "Scrooge McDuck",
      "version": "S.H.U.S.H. Agent"
    },
    {
      "amount": 4,
      "name": "Show Me More!",
      "version": ""
    },
    {
      "amount": 3,
      "name": "The White Rose",
      "version": "Jewel of the Garden"
    },
    {
      "amount": 2,
      "name": "They Never Come Back",
      "version": ""
    },
    {
      "amount": 3,
      "name": "Ursula",
      "version": "Deceiver"
    }
  ]
}