{
  "hash": "46766e25525ab458471bec741b2122f0962c064a379b5b8a179d840063996e0a",
  "inks": [
    "amethyst",
    "emerald"
  ],
  "cards": [
    {
      "amount": 4,
      "name": "Amethyst Chromicon",
      "version": ""
    },
    {
      "amount": 4,
      "name": "Bobby Zimuruski",
      "version": "Spray Cheese Kid"
    },
    {
      "amount": 4,
      "name": "Cursed Merfolk",
      "version": "Ursula's Handiwork"
    },
    {
      "amount": 4,
      "name": "Diablo",
      "version": "Obedient Raven"
    },
    {
      "amount": 4,
      "name": "Enigmatic Inkcaster",
      "version": ""
    },
    {
      "amount": 4,
      "name": "Fred",
      "version": "Mascot by Day"
    },
    {
      "amount": 4,
      "name": "Gathering Knowledge and Wisdom",
      "version": ""
    },
    {
      "amount": 4,
      "name": "Honeymaren",
      "version": "Northuldra Guide"
    },
    {
      "amount": 2,
      "name": "Improvise",
      "version": ""
    },
    {
      "amount": 2,
      "name": "Little John",
      "version": "Camp Cook"
    },
    {
      "amount": 2,
      "name": "Olivia Flaversham",
      "version": "The Toymaker's Daughter"
    },
    {
      "amount": 4,
      "name": "Pegasus",
      "version": "Gift for Hercules"
    },
    {
      "amount": 4,
      "name": "Rafiki",
      "version": "Mystical Fighter"
    },
    {
      "amount": 2,
      "name": "Royal Guard",
      "version": "Octopus Soldier"
    },
    {
      "amount": 4,
      "name": "Scrooge McDuck",
      "version": "S.H.U.S.H. Agent"
    },
    {
      "amount": 4,
      "name": "Show Me More!",
      "version": ""
    },
    {
      "amount": 4,
      "name": "Ursula",
      "version": "Deceiver"
    }
  ]
}