{
  "hash": "46ba570e46630a69692c7df18baa7d90e26f5a7072b14e0b8a1511075bbbb9fe",
  "inks": [
    "sapphire",
    "steel"
  ],
  "cards": [
    {
      "amount": 3,
      "name": "Angel",
      "version": "Experiment 624"
    },
    {
      "amount": 4,
      "name": "Basil",
      "version": "Practiced Detective"
    },
    {
      "amount": 3,
      "name": "Belle",
      "version": "Snowfield Strategist"
    },
    {
      "amount": 3,
      "name": "Clawhauser",
      "version": "Donut Detective"
    },
    {
      "amount": 3,
      "name": "Doc",
      "version": "Bold Knight"
    },
    {
      "amount": 3,
      "name": "Francine",
      "version": "Eyeing the Evidence"
    },
    {
      "amount": 3,
      "name": "Goliath",
      "version": "Clan Leader"
    },
    {
      "amount": 2,
      "name": "He Hurled His Thunderbolt",
      "version": ""
    },
    {
      "amount": 3,
      "name": "Jasmine",
      "version": "Inspired Researcher"
    },
    {
      "amount": 3,
      "name": "Judy Hopps",
      "version": "Lead Detective"
    },
    {
      "amount": 3,
      "name": "Judy Hopps",
      "version": "Uncovering Clues"
    },
    {
      "amount": 3,
      "name": "Let It Go",
      "version": ""
    },
    {
      "amount": 3,
      "name": "McHorn",
      "version": "Ice-Cold Officer"
    },
    {
      "amount": 3,
      "name": "Nick Wilde",
      "version": "Persistent Investigator"
    },
    {
      "amount": 4,
      "name": "Nick Wilde",
      "version": "Sly Fox Sleuth"
    },
    {
      "amount": 3,
      "name": "Pluto",
      "version": "Steel Champion"
    },
    {
      "amount": 4,
      "name": "Sail the Azurite Sea",
      "version": ""
    },
    {
      "amount": 3,
      "name": "Strength of a Raging Fire",
      "version": ""
    },
    {
      "amount": 4,
      "name": "Tipo",
      "version": "Growing Son"
    }
  ]
}