{
  "hash": "cf5df9cf39f0f0bf158f36096a07a0e30585f90625e195722a84a981a5b05613",
  "inks": [
    "ruby",
    "amber"
  ],
  "cards": [
    {
      "amount": 2,
      "name": "A Pirate's Life",
      "version": ""
    },
    {
      "amount": 4,
      "name": "Aladdin",
      "version": "Barreling Through"
    },
    {
      "amount": 4,
      "name": "Ariel",
      "version": "Ethereal Voice"
    },
    {
      "amount": 4,
      "name": "Della's Moon Lullaby",
      "version": ""
    },
    {
      "amount": 4,
      "name": "Liquidator",
      "version": "Iced Over"
    },
    {
      "amount": 4,
      "name": "Maleficent",
      "version": "Monstrous Dragon"
    },
    {
      "amount": 4,
      "name": "Maui",
      "version": "Half-Shark"
    },
    {
      "amount": 2,
      "name": "Mowgli",
      "version": "Man Cub"
    },
    {
      "amount": 2,
      "name": "Ohana Means Family",
      "version": ""
    },
    {
      "amount": 2,
      "name": "Or Rewrite History!",
      "version": ""
    },
    {
      "amount": 4,
      "name": "Raging Storm",
      "version": ""
    },
    {
      "amount": 4,
      "name": "Scrooge McDuck",
      "version": "Ghostly Ebenezer"
    },
    {
      "amount": 2,
      "name": "Scrooge's Counting House",
      "version": "Ebenezer's Office"
    },
    {
      "amount": 4,
      "name": "Sisu",
      "version": "Daring Visitor"
    },
    {
      "amount": 4,
      "name": "The Headless Horseman",
      "version": "Terror of Sleepy Hollow"
    },
    {
      "amount": 4,
      "name": "The Horseman Strikes!",
      "version": ""
    },
    {
      "amount": 4,
      "name": "Webby's Diary",
      "version": ""
    },
    {
      "amount": 2,
      "name": "World's Greatest Criminal Mind",
      "version": ""
    }
  ]
}