{
  "hash": "ac31164bfaa4e696bd82c2eea395e243e2b10cf9b906a86420efc134e2e25585",
  "inks": [
    "amber",
    "emerald"
  ],
  "cards": [
    {
      "amount": 4,
      "name": "Bobby Zimuruski",
      "version": "Spray Cheese Kid"
    },
    {
      "amount": 4,
      "name": "Circle of Life",
      "version": ""
    },
    {
      "amount": 4,
      "name": "Fred",
      "version": "Giant-Sized"
    },
    {
      "amount": 4,
      "name": "Fred",
      "version": "Mascot by Day"
    },
    {
      "amount": 1,
      "name": "Gazelle",
      "version": "Ballad Singer"
    },
    {
      "amount": 2,
      "name": "Lilo",
      "version": "Escape Artist"
    },
    {
      "amount": 4,
      "name": "Malicious, Mean, and Scary",
      "version": ""
    },
    {
      "amount": 4,
      "name": "Mowgli",
      "version": "Man Cub"
    },
    {
      "amount": 4,
      "name": "Prince Phillip",
      "version": "Royal Explorer"
    },
    {
      "amount": 4,
      "name": "Prince Phillip",
      "version": "Vanquisher of Foes"
    },
    {
      "amount": 3,
      "name": "Simba",
      "version": "King in the Making"
    },
    {
      "amount": 4,
      "name": "Stitch",
      "version": "Carefree Surfer"
    },
    {
      "amount": 4,
      "name": "Tramp",
      "version": "Street-Smart Dog"
    },
    {
      "amount": 2,
      "name": "Under the Sea",
      "version": ""
    },
    {
      "amount": 2,
      "name": "Ursula",
      "version": "Deceiver"
    },
    {
      "amount": 4,
      "name": "Ursula",
      "version": "Vanessa"
    },
    {
      "amount": 2,
      "name": "Webby Vanderquack",
      "version": "Junior Prospector"
    },
    {
      "amount": 4,
      "name": "Webby Vanderquack",
      "version": "Mystery Enthusiast"
    }
  ]
}